iter_model/__init__.py
iter_model/async_iter.py
iter_model/async_iter.pyi
iter_model/async_utils.py
iter_model/empty_iterator.py
iter_model/py.typed
iter_model/sync_iter.py
iter_model/sync_iter.pyi
iter_model-4.0.4.dist-info/METADATA
iter_model-4.0.4.dist-info/WHEEL
iter_model-4.0.4.dist-info/licenses/LICENSE
iter_model-4.0.4.dist-info/RECORD
