Metadata-Version: 2.4
Name: iter_model
Version: 4.0.4
Summary: iter-model uses a method approach instead of individual functions to work with iterable objects.
License: MIT
License-File: LICENSE
Keywords: iterator,iterable,async
Author: volodymyrb
Author-email: volodymyr.borysiuk0@gmail.com
Requires-Python: >=3.10
Classifier: License :: OSI Approved :: MIT License
Classifier: Programming Language :: Python :: 3
Classifier: Programming Language :: Python :: 3.10
Classifier: Programming Language :: Python :: 3.11
Classifier: Programming Language :: Python :: 3.12
Classifier: Programming Language :: Python :: 3.13
Classifier: Programming Language :: Python :: 3.14
Project-URL: Documentation, https://volodymyrbor.github.io/iter_model/
Project-URL: Homepage, https://volodymyrbor.github.io/iter_model/
Project-URL: Repository, https://github.com/VolodymyrBor/iter_model
